elitea_analyse/__init__.py
elitea_analyse/ado/__init__.py
elitea_analyse/ado/azure.py
elitea_analyse/ado/azure_base.py
elitea_analyse/ado/azure_commit.py
elitea_analyse/ado/azure_search.py
elitea_analyse/ado/main.py
elitea_analyse/ado/utils.py
elitea_analyse/aws/__init__.py
elitea_analyse/aws/read_secret.py
elitea_analyse/azure/__init__.py
elitea_analyse/azure/get_key_vault_secret.py
elitea_analyse/azure/read_blob.py
elitea_analyse/azure/upload_to_blob.py
elitea_analyse/circleci/__init__.py
elitea_analyse/circleci/circleci_base.py
elitea_analyse/clickup/__init__.py
elitea_analyse/clickup/clickup.py
elitea_analyse/clickup/clickup_main.py
elitea_analyse/clickup/clickup_transform.py
elitea_analyse/git/__init__.py
elitea_analyse/git/git_repo_provider.py
elitea_analyse/git/git_search.py
elitea_analyse/git/gitlab.py
elitea_analyse/git/main.py
elitea_analyse/github/__init__.py
elitea_analyse/github/github_base.py
elitea_analyse/github/github_org.py
elitea_analyse/github/github_repo.py
elitea_analyse/github/github_transform.py
elitea_analyse/github/main_github.py
elitea_analyse/jira/__init__.py
elitea_analyse/jira/jira_all_fields_overview.py
elitea_analyse/jira/jira_basic.py
elitea_analyse/jira/jira_connect.py
elitea_analyse/jira/jira_fields.py
elitea_analyse/jira/jira_issues.py
elitea_analyse/jira/jira_projects_overview.py
elitea_analyse/jira/jira_sprints.py
elitea_analyse/jira/jira_statuses.py
elitea_analyse/metrics/__init__.py
elitea_analyse/metrics/base_metric.py
elitea_analyse/metrics/closed_items_metrics.py
elitea_analyse/metrics/constants.py
elitea_analyse/metrics/cycle_time.py
elitea_analyse/metrics/flow_efficiency.py
elitea_analyse/metrics/flow_load.py
elitea_analyse/metrics/flow_metrics.py
elitea_analyse/metrics/items_count.py
elitea_analyse/metrics/lead_time.py
elitea_analyse/metrics/life_time.py
elitea_analyse/metrics/open_items_metrics.py
elitea_analyse/metrics/queue_metrics.py
elitea_analyse/metrics/status_based_metric.py
elitea_analyse/metrics/throughput.py
elitea_analyse-0.1.2.dist-info/METADATA
elitea_analyse-0.1.2.dist-info/WHEEL
elitea_analyse-0.1.2.dist-info/top_level.txt
elitea_analyse-0.1.2.dist-info/RECORD
